ntt_command_service/Command.py
ntt_command_service/CommandService.py
ntt_command_service/Exceptions.py
ntt_command_service/ICommand.py
ntt_command_service/ICommandService.py
ntt_command_service/__init__.py
tests/CommandServiceTest.py
tests/__init__.py
ntt_command_service-1.0.4.dist-info/LICENSE
ntt_command_service-1.0.4.dist-info/METADATA
ntt_command_service-1.0.4.dist-info/WHEEL
ntt_command_service-1.0.4.dist-info/top_level.txt
ntt_command_service-1.0.4.dist-info/RECORD
