Metadata-Version: 2.1
Name: ntt-command-service
Version: 1.0.4
Summary: Small library for observation mechanism
Home-page: https://github.com/threezinedine/ntt-command-service
Author: threezinedine
Author-email: threezinedine@email.com
License: UNKNOWN
Project-URL: Source, https://github.com/threezinedine/ntt-command-service
Project-URL: Tracker, https://github.com/threezinedine/ntt-command-service/issues
Keywords: command,mvvm,signal,ntt
Platform: UNKNOWN
Classifier: Development Status :: 3 - Alpha
Classifier: Intended Audience :: Developers
Classifier: Programming Language :: Python :: 3
Classifier: Programming Language :: Python :: 3.6
Classifier: Programming Language :: Python :: 3.7
Classifier: Programming Language :: Python :: 3.8
Classifier: Programming Language :: Python :: 3.9
License-File: LICENSE
Requires-Dist: ntt-signal
Requires-Dist: ntt-observable-list
